{
  "version": "7",
  "dialect": "postgresql",
  "entries": [
    {
      "idx": 0,
      "version": "7",
      "when": 1721381474714,
      "tag": "0000_marvelous_madelyne_pryor",
      "breakpoints": true
    },
    {
      "idx": 1,
      "version": "7",
      "when": 1721412333495,
      "tag": "0001_gifted_fabian_cortez",
      "breakpoints": true
    },
    {
      "idx": 2,
      "version": "7",
      "when": 1721453934436,
      "tag": "0002_lean_talkback",
      "breakpoints": true
    },
    {
      "idx": 3,
      "version": "7",
      "when": 1721455172131,
      "tag": "0003_happy_umar",
      "breakpoints": true
    }
  ]
}